[
  {
    "Ancestry": "Arab: - Palestinian",
    "State": "New Hampshire",
    "percapita": 0.154393934
  },
  {
    "Ancestry": "Arab: - Palestinian",
    "State": "North Dakota",
    "percapita": 0.01466255
  },
  {
    "Ancestry": "Arab: - Palestinian",
    "State": "Montana",
    "percapita": 0.037204299
  },
  {
    "Ancestry": "Arab: - Palestinian",
    "State": "Arkansas",
    "percapita": 0.192771084
  },
  {
    "Ancestry": "Arab: - Palestinian",
    "State": "Vermont",
    "percapita": 0.176549241
  },
  {
    "Ancestry": "Arab: - Palestinian",
    "State": "Hawaii",
    "percapita": 0.195782838
  },
  {
    "Ancestry": "Arab: - Palestinian",
    "State": "District of Columbia",
    "percapita": 0.235255121
  },
  {
    "Ancestry": "Arab: - Palestinian",
    "State": "West Virginia",
    "percapita": 0.064263289
  },
  {
    "Ancestry": "Arab: - Palestinian",
    "State": "Oklahoma",
    "percapita": 0.836221698
  },
  {
    "Ancestry": "Arab: - Palestinian",
    "State": "Mississippi",
    "percapita": 0.356224672
  },
  {
    "Ancestry": "Arab: - Palestinian",
    "State": "South Carolina",
    "percapita": 3.035719518
  },
  {
    "Ancestry": "Arab: - Palestinian",
    "State": "Idaho",
    "percapita": 0.052792654
  },
  {
    "Ancestry": "Arab: - Palestinian",
    "State": "Tennessee",
    "percapita": 0.542717023
  },
  {
    "Ancestry": "Arab: - Palestinian",
    "State": "Rhode Island",
    "percapita": 0.275220891
  },
  {
    "Ancestry": "Arab: - Palestinian",
    "State": "New Mexico",
    "percapita": 0.081534564
  },
  {
    "Ancestry": "Arab: - Palestinian",
    "State": "Kentucky",
    "percapita": 1.234494619
  },
  {
    "Ancestry": "Arab: - Palestinian",
    "State": "South Dakota",
    "percapita": 0.019849292
  },
  {
    "Ancestry": "Arab: - Palestinian",
    "State": "Alaska",
    "percapita": 0.188665679
  },
  {
    "Ancestry": "Arab: - Palestinian",
    "State": "Iowa",
    "percapita": 1.284425974
  },
  {
    "Ancestry": "Arab: - Palestinian",
    "State": "Oregon",
    "percapita": 0.674893169
  },
  {
    "Ancestry": "Arab: - Palestinian",
    "State": "Kansas",
    "percapita": 0.550588801
  },
  {
    "Ancestry": "Arab: - Palestinian",
    "State": "Michigan",
    "percapita": 10.408319472
  },
  {
    "Ancestry": "Arab: - Palestinian",
    "State": "Louisiana",
    "percapita": 12.570587382
  },
  {
    "Ancestry": "Arab: - Palestinian",
    "State": "Maine",
    "percapita": 0.127166707
  },
  {
    "Ancestry": "Arab: - Palestinian",
    "State": "Illinois",
    "percapita": 19.004510483
  },
  {
    "Ancestry": "Arab: - Palestinian",
    "State": "Alabama",
    "percapita": 7.207505579
  },
  {
    "Ancestry": "Arab: - Palestinian",
    "State": "Massachusetts",
    "percapita": 1.862788004
  },
  {
    "Ancestry": "Arab: - Palestinian",
    "State": "Ohio",
    "percapita": 15.110683176
  },
  {
    "Ancestry": "Arab: - Palestinian",
    "State": "Minnesota",
    "percapita": 2.571742429
  },
  {
    "Ancestry": "Arab: - Palestinian",
    "State": "Florida",
    "percapita": 6.882998825
  },
  {
    "Ancestry": "Arab: - Palestinian",
    "State": "Indiana",
    "percapita": 3.897492409
  },
  {
    "Ancestry": "Arab: - Palestinian",
    "State": "Nebraska",
    "percapita": 0.79602719
  },
  {
    "Ancestry": "Arab: - Palestinian",
    "State": "Maryland",
    "percapita": 2.524680494
  },
  {
    "Ancestry": "Arab: - Palestinian",
    "State": "Wisconsin",
    "percapita": 25.044808466
  },
  {
    "Ancestry": "Arab: - Palestinian",
    "State": "Delaware",
    "percapita": 2.231014747
  },
  {
    "Ancestry": "Arab: - Palestinian",
    "State": "Colorado",
    "percapita": 1.921217835
  },
  {
    "Ancestry": "Arab: - Palestinian",
    "State": "Arizona",
    "percapita": 6.084880202
  },
  {
    "Ancestry": "Arab: - Palestinian",
    "State": "Washington",
    "percapita": 5.609822269
  },
  {
    "Ancestry": "Arab: - Palestinian",
    "State": "Utah",
    "percapita": 5.825441058
  },
  {
    "Ancestry": "Arab: - Palestinian",
    "State": "Nevada",
    "percapita": 3.127795703
  },
  {
    "Ancestry": "Arab: - Palestinian",
    "State": "Connecticut",
    "percapita": 7.032814815
  },
  {
    "Ancestry": "Arab: - Palestinian",
    "State": "Texas",
    "percapita": 24.686516914
  },
  {
    "Ancestry": "Arab: - Palestinian",
    "State": "North Carolina",
    "percapita": 38.405262062
  },
  {
    "Ancestry": "Arab: - Palestinian",
    "State": "New York",
    "percapita": 5.950343344
  },
  {
    "Ancestry": "Arab: - Palestinian",
    "State": "Pennsylvania",
    "percapita": 24.507829522
  },
  {
    "Ancestry": "Arab: - Palestinian",
    "State": "Georgia",
    "percapita": 13.07446457
  },
  {
    "Ancestry": "Arab: - Palestinian",
    "State": "Missouri",
    "percapita": 12.808000164
  },
  {
    "Ancestry": "Arab: - Palestinian",
    "State": "New Jersey",
    "percapita": 29.517082124
  },
  {
    "Ancestry": "Arab: - Palestinian",
    "State": "Virginia",
    "percapita": 5.483230971
  },
  {
    "Ancestry": "Arab: - Palestinian",
    "State": "California",
    "percapita": 32.864899906
  }
]