[
  {
    "Ancestry": "British",
    "State": "Wyoming",
    "per capita": 41.119364276
  },
  {
    "Ancestry": "British",
    "State": "New Hampshire",
    "per capita": 56.179732939
  },
  {
    "Ancestry": "British",
    "State": "North Dakota",
    "per capita": 14.320835396
  },
  {
    "Ancestry": "British",
    "State": "Montana",
    "per capita": 35.659191914
  },
  {
    "Ancestry": "British",
    "State": "Arkansas",
    "per capita": 29.011899733
  },
  {
    "Ancestry": "British",
    "State": "Vermont",
    "per capita": 74.980608463
  },
  {
    "Ancestry": "British",
    "State": "Hawaii",
    "per capita": 27.381704626
  },
  {
    "Ancestry": "British",
    "State": "District of Columbia",
    "per capita": 72.424505952
  },
  {
    "Ancestry": "British",
    "State": "West Virginia",
    "per capita": 27.849146583
  },
  {
    "Ancestry": "British",
    "State": "Oklahoma",
    "per capita": 34.055766672
  },
  {
    "Ancestry": "British",
    "State": "Mississippi",
    "per capita": 25.259854533
  },
  {
    "Ancestry": "British",
    "State": "South Carolina",
    "per capita": 44.972748993
  },
  {
    "Ancestry": "British",
    "State": "Idaho",
    "per capita": 51.344049181
  },
  {
    "Ancestry": "British",
    "State": "Tennessee",
    "per capita": 41.243774957
  },
  {
    "Ancestry": "British",
    "State": "Rhode Island",
    "per capita": 31.217629716
  },
  {
    "Ancestry": "British",
    "State": "New Mexico",
    "per capita": 33.822855313
  },
  {
    "Ancestry": "British",
    "State": "Kentucky",
    "per capita": 39.325182051
  },
  {
    "Ancestry": "British",
    "State": "South Dakota",
    "per capita": 21.226594778
  },
  {
    "Ancestry": "British",
    "State": "Alaska",
    "per capita": 58.868082288
  },
  {
    "Ancestry": "British",
    "State": "Iowa",
    "per capita": 24.575765514
  },
  {
    "Ancestry": "British",
    "State": "Oregon",
    "per capita": 67.346071609
  },
  {
    "Ancestry": "British",
    "State": "Kansas",
    "per capita": 38.539666208
  },
  {
    "Ancestry": "British",
    "State": "Michigan",
    "per capita": 32.247625273
  },
  {
    "Ancestry": "British",
    "State": "Louisiana",
    "per capita": 23.111287754
  },
  {
    "Ancestry": "British",
    "State": "Maine",
    "per capita": 56.469905397
  },
  {
    "Ancestry": "British",
    "State": "Illinois",
    "per capita": 27.459943574
  },
  {
    "Ancestry": "British",
    "State": "Alabama",
    "per capita": 40.452618965
  },
  {
    "Ancestry": "British",
    "State": "Massachusetts",
    "per capita": 45.334544627
  },
  {
    "Ancestry": "British",
    "State": "Ohio",
    "per capita": 34.774394667
  },
  {
    "Ancestry": "British",
    "State": "Minnesota",
    "per capita": 25.020280647
  },
  {
    "Ancestry": "British",
    "State": "Florida",
    "per capita": 47.111346098
  },
  {
    "Ancestry": "British",
    "State": "Indiana",
    "per capita": 35.841321357
  },
  {
    "Ancestry": "British",
    "State": "Nebraska",
    "per capita": 25.176680558
  },
  {
    "Ancestry": "British",
    "State": "Maryland",
    "per capita": 46.780615845
  },
  {
    "Ancestry": "British",
    "State": "Wisconsin",
    "per capita": 22.776993881
  },
  {
    "Ancestry": "British",
    "State": "Delaware",
    "per capita": 43.233641224
  },
  {
    "Ancestry": "British",
    "State": "Colorado",
    "per capita": 56.885291753
  },
  {
    "Ancestry": "British",
    "State": "Arizona",
    "per capita": 39.648018178
  },
  {
    "Ancestry": "British",
    "State": "Washington",
    "per capita": 64.704108033
  },
  {
    "Ancestry": "British",
    "State": "Utah",
    "per capita": 138.074594397
  },
  {
    "Ancestry": "British",
    "State": "Nevada",
    "per capita": 35.085074525
  },
  {
    "Ancestry": "British",
    "State": "Connecticut",
    "per capita": 46.64305413
  },
  {
    "Ancestry": "British",
    "State": "Texas",
    "per capita": 36.08381925
  },
  {
    "Ancestry": "British",
    "State": "North Carolina",
    "per capita": 48.603353753
  },
  {
    "Ancestry": "British",
    "State": "New York",
    "per capita": 29.354975004
  },
  {
    "Ancestry": "British",
    "State": "Pennsylvania",
    "per capita": 31.380577263
  },
  {
    "Ancestry": "British",
    "State": "Georgia",
    "per capita": 44.530526496
  },
  {
    "Ancestry": "British",
    "State": "Missouri",
    "per capita": 34.430104019
  },
  {
    "Ancestry": "British",
    "State": "New Jersey",
    "per capita": 28.581897311
  },
  {
    "Ancestry": "British",
    "State": "Virginia",
    "per capita": 63.526500221
  },
  {
    "Ancestry": "British",
    "State": "California",
    "per capita": 37.886218671
  }
]