[
  {
    "Ancestry": "Finnish",
    "State": "New Hampshire",
    "percapita": 9.609344189
  },
  {
    "Ancestry": "Finnish",
    "State": "North Dakota",
    "percapita": 3.305111374
  },
  {
    "Ancestry": "Finnish",
    "State": "Montana",
    "percapita": 43.183561227
  },
  {
    "Ancestry": "Finnish",
    "State": "Arkansas",
    "percapita": 0.391727337
  },
  {
    "Ancestry": "Finnish",
    "State": "Vermont",
    "percapita": 2.733510691
  },
  {
    "Ancestry": "Finnish",
    "State": "Hawaii",
    "percapita": 8.889764473
  },
  {
    "Ancestry": "Finnish",
    "State": "District of Columbia",
    "percapita": 0.386059686
  },
  {
    "Ancestry": "Finnish",
    "State": "West Virginia",
    "percapita": 1.443318737
  },
  {
    "Ancestry": "Finnish",
    "State": "Oklahoma",
    "percapita": 6.755260829
  },
  {
    "Ancestry": "Finnish",
    "State": "Mississippi",
    "percapita": 1.362229531
  },
  {
    "Ancestry": "Finnish",
    "State": "South Carolina",
    "percapita": 63.832156357
  },
  {
    "Ancestry": "Finnish",
    "State": "Idaho",
    "percapita": 4.732706136
  },
  {
    "Ancestry": "Finnish",
    "State": "Tennessee",
    "percapita": 1.532442941
  },
  {
    "Ancestry": "Finnish",
    "State": "Rhode Island",
    "percapita": 2.874299377
  },
  {
    "Ancestry": "Finnish",
    "State": "New Mexico",
    "percapita": 0.991581835
  },
  {
    "Ancestry": "Finnish",
    "State": "Kentucky",
    "percapita": 5.35306116
  },
  {
    "Ancestry": "Finnish",
    "State": "South Dakota",
    "percapita": 6.096786369
  },
  {
    "Ancestry": "Finnish",
    "State": "Alaska",
    "percapita": 6.78602222
  },
  {
    "Ancestry": "Finnish",
    "State": "Iowa",
    "percapita": 9.696899575
  },
  {
    "Ancestry": "Finnish",
    "State": "Oregon",
    "percapita": 17.068619118
  },
  {
    "Ancestry": "Finnish",
    "State": "Kansas",
    "percapita": 4.098827744
  },
  {
    "Ancestry": "Finnish",
    "State": "Michigan",
    "percapita": 183.494274416
  },
  {
    "Ancestry": "Finnish",
    "State": "Louisiana",
    "percapita": 10.480501681
  },
  {
    "Ancestry": "Finnish",
    "State": "Maine",
    "percapita": 10.288790573
  },
  {
    "Ancestry": "Finnish",
    "State": "Illinois",
    "percapita": 25.043751909
  },
  {
    "Ancestry": "Finnish",
    "State": "Alabama",
    "percapita": 22.993435876
  },
  {
    "Ancestry": "Finnish",
    "State": "Massachusetts",
    "percapita": 23.975070528
  },
  {
    "Ancestry": "Finnish",
    "State": "Ohio",
    "percapita": 46.054061692
  },
  {
    "Ancestry": "Finnish",
    "State": "Minnesota",
    "percapita": 322.135788668
  },
  {
    "Ancestry": "Finnish",
    "State": "Florida",
    "percapita": 25.618620661
  },
  {
    "Ancestry": "Finnish",
    "State": "Indiana",
    "percapita": 17.34722055
  },
  {
    "Ancestry": "Finnish",
    "State": "Nebraska",
    "percapita": 5.688424391
  },
  {
    "Ancestry": "Finnish",
    "State": "Maryland",
    "percapita": 7.290885889
  },
  {
    "Ancestry": "Finnish",
    "State": "Wisconsin",
    "percapita": 657.721521588
  },
  {
    "Ancestry": "Finnish",
    "State": "Delaware",
    "percapita": 8.666050482
  },
  {
    "Ancestry": "Finnish",
    "State": "Colorado",
    "percapita": 31.709825486
  },
  {
    "Ancestry": "Finnish",
    "State": "Arizona",
    "percapita": 51.109622572
  },
  {
    "Ancestry": "Finnish",
    "State": "Washington",
    "percapita": 244.135357769
  },
  {
    "Ancestry": "Finnish",
    "State": "Utah",
    "percapita": 90.701319263
  },
  {
    "Ancestry": "Finnish",
    "State": "Nevada",
    "percapita": 34.759985017
  },
  {
    "Ancestry": "Finnish",
    "State": "Connecticut",
    "percapita": 67.730923223
  },
  {
    "Ancestry": "Finnish",
    "State": "Texas",
    "percapita": 51.741444329
  },
  {
    "Ancestry": "Finnish",
    "State": "North Carolina",
    "percapita": 103.964667159
  },
  {
    "Ancestry": "Finnish",
    "State": "New York",
    "percapita": 16.311402575
  },
  {
    "Ancestry": "Finnish",
    "State": "Pennsylvania",
    "percapita": 84.497992272
  },
  {
    "Ancestry": "Finnish",
    "State": "Georgia",
    "percapita": 40.58296896
  },
  {
    "Ancestry": "Finnish",
    "State": "Missouri",
    "percapita": 39.772211036
  },
  {
    "Ancestry": "Finnish",
    "State": "New Jersey",
    "percapita": 30.629486779
  },
  {
    "Ancestry": "Finnish",
    "State": "Virginia",
    "percapita": 11.3403186
  },
  {
    "Ancestry": "Finnish",
    "State": "California",
    "percapita": 98.48640724
  }
]