[
  {
    "Ancestry": "Lithuanian",
    "State": "Wyoming",
    "per capita": 8.25126294
  },
  {
    "Ancestry": "Lithuanian",
    "State": "New Hampshire",
    "per capita": 57.694641219
  },
  {
    "Ancestry": "Lithuanian",
    "State": "North Dakota",
    "per capita": 3.448359798
  },
  {
    "Ancestry": "Lithuanian",
    "State": "Montana",
    "per capita": 12.593068048
  },
  {
    "Ancestry": "Lithuanian",
    "State": "Arkansas",
    "per capita": 5.009491402
  },
  {
    "Ancestry": "Lithuanian",
    "State": "Vermont",
    "per capita": 35.048407021
  },
  {
    "Ancestry": "Lithuanian",
    "State": "Hawaii",
    "per capita": 7.502319379
  },
  {
    "Ancestry": "Lithuanian",
    "State": "District of Columbia",
    "per capita": 29.412969936
  },
  {
    "Ancestry": "Lithuanian",
    "State": "West Virginia",
    "per capita": 9.284850345
  },
  {
    "Ancestry": "Lithuanian",
    "State": "Oklahoma",
    "per capita": 4.79106644
  },
  {
    "Ancestry": "Lithuanian",
    "State": "Mississippi",
    "per capita": 2.224390205
  },
  {
    "Ancestry": "Lithuanian",
    "State": "South Carolina",
    "per capita": 9.260251771
  },
  {
    "Ancestry": "Lithuanian",
    "State": "Idaho",
    "per capita": 6.564843276
  },
  {
    "Ancestry": "Lithuanian",
    "State": "Tennessee",
    "per capita": 7.067874807
  },
  {
    "Ancestry": "Lithuanian",
    "State": "Rhode Island",
    "per capita": 39.481677412
  },
  {
    "Ancestry": "Lithuanian",
    "State": "New Mexico",
    "per capita": 8.165625545
  },
  {
    "Ancestry": "Lithuanian",
    "State": "Kentucky",
    "per capita": 4.971159796
  },
  {
    "Ancestry": "Lithuanian",
    "State": "South Dakota",
    "per capita": 4.090602749
  },
  {
    "Ancestry": "Lithuanian",
    "State": "Alaska",
    "per capita": 13.777058686
  },
  {
    "Ancestry": "Lithuanian",
    "State": "Iowa",
    "per capita": 8.886025221
  },
  {
    "Ancestry": "Lithuanian",
    "State": "Oregon",
    "per capita": 15.094809154
  },
  {
    "Ancestry": "Lithuanian",
    "State": "Kansas",
    "per capita": 8.229968034
  },
  {
    "Ancestry": "Lithuanian",
    "State": "Michigan",
    "per capita": 28.37169422
  },
  {
    "Ancestry": "Lithuanian",
    "State": "Louisiana",
    "per capita": 3.623908419
  },
  {
    "Ancestry": "Lithuanian",
    "State": "Maine",
    "per capita": 44.185013183
  },
  {
    "Ancestry": "Lithuanian",
    "State": "Illinois",
    "per capita": 67.092475649
  },
  {
    "Ancestry": "Lithuanian",
    "State": "Alabama",
    "per capita": 4.476863729
  },
  {
    "Ancestry": "Lithuanian",
    "State": "Massachusetts",
    "per capita": 72.894033986
  },
  {
    "Ancestry": "Lithuanian",
    "State": "Ohio",
    "per capita": 19.212253614
  },
  {
    "Ancestry": "Lithuanian",
    "State": "Minnesota",
    "per capita": 9.722982944
  },
  {
    "Ancestry": "Lithuanian",
    "State": "Florida",
    "per capita": 19.125537612
  },
  {
    "Ancestry": "Lithuanian",
    "State": "Indiana",
    "per capita": 15.986405643
  },
  {
    "Ancestry": "Lithuanian",
    "State": "Nebraska",
    "per capita": 16.035052827
  },
  {
    "Ancestry": "Lithuanian",
    "State": "Maryland",
    "per capita": 30.044807859
  },
  {
    "Ancestry": "Lithuanian",
    "State": "Wisconsin",
    "per capita": 23.570732344
  },
  {
    "Ancestry": "Lithuanian",
    "State": "Delaware",
    "per capita": 29.499344815
  },
  {
    "Ancestry": "Lithuanian",
    "State": "Colorado",
    "per capita": 19.408625981
  },
  {
    "Ancestry": "Lithuanian",
    "State": "Arizona",
    "per capita": 16.785303211
  },
  {
    "Ancestry": "Lithuanian",
    "State": "Washington",
    "per capita": 14.342500846
  },
  {
    "Ancestry": "Lithuanian",
    "State": "Utah",
    "per capita": 6.021267443
  },
  {
    "Ancestry": "Lithuanian",
    "State": "Nevada",
    "per capita": 16.0156444
  },
  {
    "Ancestry": "Lithuanian",
    "State": "Connecticut",
    "per capita": 80.232392289
  },
  {
    "Ancestry": "Lithuanian",
    "State": "Texas",
    "per capita": 5.736552322
  },
  {
    "Ancestry": "Lithuanian",
    "State": "North Carolina",
    "per capita": 9.142229397
  },
  {
    "Ancestry": "Lithuanian",
    "State": "New York",
    "per capita": 22.526328701
  },
  {
    "Ancestry": "Lithuanian",
    "State": "Pennsylvania",
    "per capita": 58.195654736
  },
  {
    "Ancestry": "Lithuanian",
    "State": "Georgia",
    "per capita": 8.582455801
  },
  {
    "Ancestry": "Lithuanian",
    "State": "Missouri",
    "per capita": 9.047446982
  },
  {
    "Ancestry": "Lithuanian",
    "State": "New Jersey",
    "per capita": 37.086989234
  },
  {
    "Ancestry": "Lithuanian",
    "State": "Virginia",
    "per capita": 17.03159715
  },
  {
    "Ancestry": "Lithuanian",
    "State": "California",
    "per capita": 12.746601379
  }
]