[
  {
    "Ancestry": "Northern European",
    "State": "New Hampshire",
    "percapita": 1.250814624
  },
  {
    "Ancestry": "Northern European",
    "State": "North Dakota",
    "percapita": 0.38640133
  },
  {
    "Ancestry": "Northern European",
    "State": "Montana",
    "percapita": 13.143747313
  },
  {
    "Ancestry": "Northern European",
    "State": "Arkansas",
    "percapita": 0.300238387
  },
  {
    "Ancestry": "Northern European",
    "State": "Vermont",
    "percapita": 2.118590887
  },
  {
    "Ancestry": "Northern European",
    "State": "Hawaii",
    "percapita": 9.122256593
  },
  {
    "Ancestry": "Northern European",
    "State": "District of Columbia",
    "percapita": 0.383546277
  },
  {
    "Ancestry": "Northern European",
    "State": "West Virginia",
    "percapita": 1.931372365
  },
  {
    "Ancestry": "Northern European",
    "State": "Oklahoma",
    "percapita": 3.594242059
  },
  {
    "Ancestry": "Northern European",
    "State": "Mississippi",
    "percapita": 3.196126914
  },
  {
    "Ancestry": "Northern European",
    "State": "South Carolina",
    "percapita": 24.965569783
  },
  {
    "Ancestry": "Northern European",
    "State": "Idaho",
    "percapita": 2.488241989
  },
  {
    "Ancestry": "Northern European",
    "State": "Tennessee",
    "percapita": 1.025338245
  },
  {
    "Ancestry": "Northern European",
    "State": "Rhode Island",
    "percapita": 1.545789514
  },
  {
    "Ancestry": "Northern European",
    "State": "New Mexico",
    "percapita": 1.499526973
  },
  {
    "Ancestry": "Northern European",
    "State": "Kentucky",
    "percapita": 3.729292106
  },
  {
    "Ancestry": "Northern European",
    "State": "South Dakota",
    "percapita": 1.039797525
  },
  {
    "Ancestry": "Northern European",
    "State": "Alaska",
    "percapita": 4.012488182
  },
  {
    "Ancestry": "Northern European",
    "State": "Iowa",
    "percapita": 12.203768499
  },
  {
    "Ancestry": "Northern European",
    "State": "Oregon",
    "percapita": 8.907338576
  },
  {
    "Ancestry": "Northern European",
    "State": "Kansas",
    "percapita": 6.029287246
  },
  {
    "Ancestry": "Northern European",
    "State": "Michigan",
    "percapita": 12.850976137
  },
  {
    "Ancestry": "Northern European",
    "State": "Louisiana",
    "percapita": 9.916629639
  },
  {
    "Ancestry": "Northern European",
    "State": "Maine",
    "percapita": 1.979450195
  },
  {
    "Ancestry": "Northern European",
    "State": "Illinois",
    "percapita": 14.112785562
  },
  {
    "Ancestry": "Northern European",
    "State": "Alabama",
    "percapita": 24.147179707
  },
  {
    "Ancestry": "Northern European",
    "State": "Massachusetts",
    "percapita": 7.382533608
  },
  {
    "Ancestry": "Northern European",
    "State": "Ohio",
    "percapita": 15.471689258
  },
  {
    "Ancestry": "Northern European",
    "State": "Minnesota",
    "percapita": 37.944890566
  },
  {
    "Ancestry": "Northern European",
    "State": "Florida",
    "percapita": 8.737942249
  },
  {
    "Ancestry": "Northern European",
    "State": "Indiana",
    "percapita": 11.927421032
  },
  {
    "Ancestry": "Northern European",
    "State": "Nebraska",
    "percapita": 4.723329479
  },
  {
    "Ancestry": "Northern European",
    "State": "Maryland",
    "percapita": 7.4228275
  },
  {
    "Ancestry": "Northern European",
    "State": "Wisconsin",
    "percapita": 84.310103689
  },
  {
    "Ancestry": "Northern European",
    "State": "Delaware",
    "percapita": 7.315300056
  },
  {
    "Ancestry": "Northern European",
    "State": "Colorado",
    "percapita": 30.005474498
  },
  {
    "Ancestry": "Northern European",
    "State": "Arizona",
    "percapita": 18.065857619
  },
  {
    "Ancestry": "Northern European",
    "State": "Washington",
    "percapita": 126.183169885
  },
  {
    "Ancestry": "Northern European",
    "State": "Utah",
    "percapita": 101.649956429
  },
  {
    "Ancestry": "Northern European",
    "State": "Nevada",
    "percapita": 13.242257952
  },
  {
    "Ancestry": "Northern European",
    "State": "Connecticut",
    "percapita": 33.315020938
  },
  {
    "Ancestry": "Northern European",
    "State": "Texas",
    "percapita": 42.655175062
  },
  {
    "Ancestry": "Northern European",
    "State": "North Carolina",
    "percapita": 73.294549428
  },
  {
    "Ancestry": "Northern European",
    "State": "New York",
    "percapita": 10.939299458
  },
  {
    "Ancestry": "Northern European",
    "State": "Pennsylvania",
    "percapita": 61.089508545
  },
  {
    "Ancestry": "Northern European",
    "State": "Georgia",
    "percapita": 34.5458913
  },
  {
    "Ancestry": "Northern European",
    "State": "Missouri",
    "percapita": 50.518816818
  },
  {
    "Ancestry": "Northern European",
    "State": "New Jersey",
    "percapita": 15.928483888
  },
  {
    "Ancestry": "Northern European",
    "State": "Virginia",
    "percapita": 11.348815342
  },
  {
    "Ancestry": "Northern European",
    "State": "California",
    "percapita": 90.823780879
  }
]