[
  {
    "Ancestry": "Swedish",
    "State": "Wyoming",
    "percapita": 287.253510638
  },
  {
    "Ancestry": "Swedish",
    "State": "New Hampshire",
    "percapita": 200.563304701
  },
  {
    "Ancestry": "Swedish",
    "State": "North Dakota",
    "percapita": 423.377445293
  },
  {
    "Ancestry": "Swedish",
    "State": "Montana",
    "percapita": 298.951033579
  },
  {
    "Ancestry": "Swedish",
    "State": "Arkansas",
    "percapita": 54.80774644
  },
  {
    "Ancestry": "Swedish",
    "State": "Vermont",
    "percapita": 159.122321494
  },
  {
    "Ancestry": "Swedish",
    "State": "Hawaii",
    "percapita": 69.000204993
  },
  {
    "Ancestry": "Swedish",
    "State": "District of Columbia",
    "percapita": 65.928762333
  },
  {
    "Ancestry": "Swedish",
    "State": "West Virginia",
    "percapita": 39.117431199
  },
  {
    "Ancestry": "Swedish",
    "State": "Oklahoma",
    "percapita": 70.259519537
  },
  {
    "Ancestry": "Swedish",
    "State": "Mississippi",
    "percapita": 27.313908551
  },
  {
    "Ancestry": "Swedish",
    "State": "South Carolina",
    "percapita": 46.357130766
  },
  {
    "Ancestry": "Swedish",
    "State": "Idaho",
    "percapita": 271.611977994
  },
  {
    "Ancestry": "Swedish",
    "State": "Tennessee",
    "percapita": 52.950276608
  },
  {
    "Ancestry": "Swedish",
    "State": "Rhode Island",
    "percapita": 167.356442972
  },
  {
    "Ancestry": "Swedish",
    "State": "New Mexico",
    "percapita": 77.734070078
  },
  {
    "Ancestry": "Swedish",
    "State": "Kentucky",
    "percapita": 36.463479762
  },
  {
    "Ancestry": "Swedish",
    "State": "South Dakota",
    "percapita": 332.628124359
  },
  {
    "Ancestry": "Swedish",
    "State": "Alaska",
    "percapita": 235.404461867
  },
  {
    "Ancestry": "Swedish",
    "State": "Iowa",
    "percapita": 288.855360227
  },
  {
    "Ancestry": "Swedish",
    "State": "Oregon",
    "percapita": 282.310460403
  },
  {
    "Ancestry": "Swedish",
    "State": "Kansas",
    "percapita": 233.018287402
  },
  {
    "Ancestry": "Swedish",
    "State": "Michigan",
    "percapita": 151.947395513
  },
  {
    "Ancestry": "Swedish",
    "State": "Louisiana",
    "percapita": 26.71153861
  },
  {
    "Ancestry": "Swedish",
    "State": "Maine",
    "percapita": 185.829670045
  },
  {
    "Ancestry": "Swedish",
    "State": "Illinois",
    "percapita": 213.086677774
  },
  {
    "Ancestry": "Swedish",
    "State": "Alabama",
    "percapita": 35.50765387
  },
  {
    "Ancestry": "Swedish",
    "State": "Massachusetts",
    "percapita": 172.714534095
  },
  {
    "Ancestry": "Swedish",
    "State": "Ohio",
    "percapita": 62.62547801
  },
  {
    "Ancestry": "Swedish",
    "State": "Minnesota",
    "percapita": 834.415548124
  },
  {
    "Ancestry": "Swedish",
    "State": "Florida",
    "percapita": 75.037838122
  },
  {
    "Ancestry": "Swedish",
    "State": "Indiana",
    "percapita": 89.707898688
  },
  {
    "Ancestry": "Swedish",
    "State": "Nebraska",
    "percapita": 434.891679684
  },
  {
    "Ancestry": "Swedish",
    "State": "Maryland",
    "percapita": 56.733083942
  },
  {
    "Ancestry": "Swedish",
    "State": "Wisconsin",
    "percapita": 255.033205015
  },
  {
    "Ancestry": "Swedish",
    "State": "Delaware",
    "percapita": 78.867994707
  },
  {
    "Ancestry": "Swedish",
    "State": "Colorado",
    "percapita": 235.903960256
  },
  {
    "Ancestry": "Swedish",
    "State": "Arizona",
    "percapita": 150.155597191
  },
  {
    "Ancestry": "Swedish",
    "State": "Washington",
    "percapita": 325.180237144
  },
  {
    "Ancestry": "Swedish",
    "State": "Utah",
    "percapita": 383.009695872
  },
  {
    "Ancestry": "Swedish",
    "State": "Nevada",
    "percapita": 119.869014783
  },
  {
    "Ancestry": "Swedish",
    "State": "Connecticut",
    "percapita": 170.615821215
  },
  {
    "Ancestry": "Swedish",
    "State": "Texas",
    "percapita": 55.547439737
  },
  {
    "Ancestry": "Swedish",
    "State": "North Carolina",
    "percapita": 53.736115698
  },
  {
    "Ancestry": "Swedish",
    "State": "New York",
    "percapita": 62.003743804
  },
  {
    "Ancestry": "Swedish",
    "State": "Pennsylvania",
    "percapita": 81.664419499
  },
  {
    "Ancestry": "Swedish",
    "State": "Georgia",
    "percapita": 45.533760713
  },
  {
    "Ancestry": "Swedish",
    "State": "Missouri",
    "percapita": 98.154739709
  },
  {
    "Ancestry": "Swedish",
    "State": "New Jersey",
    "percapita": 57.47258249
  },
  {
    "Ancestry": "Swedish",
    "State": "Virginia",
    "percapita": 69.811412984
  },
  {
    "Ancestry": "Swedish",
    "State": "California",
    "percapita": 107.385606598
  }
]
