[
  {
    "Ancestry": "West Indian (except Hispanic groups): - Belizean",
    "State": "Wyoming",
    "percapita": 0
  },
  {
    "Ancestry": "West Indian (except Hispanic groups): - Belizean",
    "State": "New Hampshire",
    "percapita": 0.354232284
  },
  {
    "Ancestry": "West Indian (except Hispanic groups): - Belizean",
    "State": "North Dakota",
    "percapita": 0
  },
  {
    "Ancestry": "West Indian (except Hispanic groups): - Belizean",
    "State": "Montana",
    "percapita": 0.889037387
  },
  {
    "Ancestry": "West Indian (except Hispanic groups): - Belizean",
    "State": "Arkansas",
    "percapita": 0.205638611
  },
  {
    "Ancestry": "West Indian (except Hispanic groups): - Belizean",
    "State": "Vermont",
    "percapita": 0
  },
  {
    "Ancestry": "West Indian (except Hispanic groups): - Belizean",
    "State": "Hawaii",
    "percapita": 1.176420034
  },
  {
    "Ancestry": "West Indian (except Hispanic groups): - Belizean",
    "State": "District of Columbia",
    "percapita": 0.956149177
  },
  {
    "Ancestry": "West Indian (except Hispanic groups): - Belizean",
    "State": "West Virginia",
    "percapita": 0
  },
  {
    "Ancestry": "West Indian (except Hispanic groups): - Belizean",
    "State": "Oklahoma",
    "percapita": 0.402263921
  },
  {
    "Ancestry": "West Indian (except Hispanic groups): - Belizean",
    "State": "Mississippi",
    "percapita": 0.177016037
  },
  {
    "Ancestry": "West Indian (except Hispanic groups): - Belizean",
    "State": "South Carolina",
    "percapita": 0.707710862
  },
  {
    "Ancestry": "West Indian (except Hispanic groups): - Belizean",
    "State": "Idaho",
    "percapita": 0.593466727
  },
  {
    "Ancestry": "West Indian (except Hispanic groups): - Belizean",
    "State": "Tennessee",
    "percapita": 0.36339473
  },
  {
    "Ancestry": "West Indian (except Hispanic groups): - Belizean",
    "State": "Rhode Island",
    "percapita": 0.957189011
  },
  {
    "Ancestry": "West Indian (except Hispanic groups): - Belizean",
    "State": "New Mexico",
    "percapita": 0.373998117
  },
  {
    "Ancestry": "West Indian (except Hispanic groups): - Belizean",
    "State": "Kentucky",
    "percapita": 0.154074233
  },
  {
    "Ancestry": "West Indian (except Hispanic groups): - Belizean",
    "State": "South Dakota",
    "percapita": 0.281302195
  },
  {
    "Ancestry": "West Indian (except Hispanic groups): - Belizean",
    "State": "Alaska",
    "percapita": 0.732966669
  },
  {
    "Ancestry": "West Indian (except Hispanic groups): - Belizean",
    "State": "Iowa",
    "percapita": 0.360461726
  },
  {
    "Ancestry": "West Indian (except Hispanic groups): - Belizean",
    "State": "Oregon",
    "percapita": 0.498710531
  },
  {
    "Ancestry": "West Indian (except Hispanic groups): - Belizean",
    "State": "Kansas",
    "percapita": 0.137740051
  },
  {
    "Ancestry": "West Indian (except Hispanic groups): - Belizean",
    "State": "Michigan",
    "percapita": 0.327955635
  },
  {
    "Ancestry": "West Indian (except Hispanic groups): - Belizean",
    "State": "Louisiana",
    "percapita": 1.058138244
  },
  {
    "Ancestry": "West Indian (except Hispanic groups): - Belizean",
    "State": "Maine",
    "percapita": 0
  },
  {
    "Ancestry": "West Indian (except Hispanic groups): - Belizean",
    "State": "Illinois",
    "percapita": 3.572820479
  },
  {
    "Ancestry": "West Indian (except Hispanic groups): - Belizean",
    "State": "Alabama",
    "percapita": 0.152596921
  },
  {
    "Ancestry": "West Indian (except Hispanic groups): - Belizean",
    "State": "Massachusetts",
    "percapita": 0.714560187
  },
  {
    "Ancestry": "West Indian (except Hispanic groups): - Belizean",
    "State": "Ohio",
    "percapita": 0.163875564
  },
  {
    "Ancestry": "West Indian (except Hispanic groups): - Belizean",
    "State": "Minnesota",
    "percapita": 0.500259017
  },
  {
    "Ancestry": "West Indian (except Hispanic groups): - Belizean",
    "State": "Florida",
    "percapita": 2.277651613
  },
  {
    "Ancestry": "West Indian (except Hispanic groups): - Belizean",
    "State": "Indiana",
    "percapita": 0.112174665
  },
  {
    "Ancestry": "West Indian (except Hispanic groups): - Belizean",
    "State": "Nebraska",
    "percapita": 0.372042989
  },
  {
    "Ancestry": "West Indian (except Hispanic groups): - Belizean",
    "State": "Maryland",
    "percapita": 0.667625214
  },
  {
    "Ancestry": "West Indian (except Hispanic groups): - Belizean",
    "State": "Wisconsin",
    "percapita": 0.317842754
  },
  {
    "Ancestry": "West Indian (except Hispanic groups): - Belizean",
    "State": "Delaware",
    "percapita": 0.748171789
  },
  {
    "Ancestry": "West Indian (except Hispanic groups): - Belizean",
    "State": "Colorado",
    "percapita": 0.48731615
  },
  {
    "Ancestry": "West Indian (except Hispanic groups): - Belizean",
    "State": "Arizona",
    "percapita": 1.014635109
  },
  {
    "Ancestry": "West Indian (except Hispanic groups): - Belizean",
    "State": "Washington",
    "percapita": 0.66557814
  },
  {
    "Ancestry": "West Indian (except Hispanic groups): - Belizean",
    "State": "Utah",
    "percapita": 0.1053382
  },
  {
    "Ancestry": "West Indian (except Hispanic groups): - Belizean",
    "State": "Nevada",
    "percapita": 2.560671537
  },
  {
    "Ancestry": "West Indian (except Hispanic groups): - Belizean",
    "State": "Connecticut",
    "percapita": 0.683964671
  },
  {
    "Ancestry": "West Indian (except Hispanic groups): - Belizean",
    "State": "Texas",
    "percapita": 1.570281038
  },
  {
    "Ancestry": "West Indian (except Hispanic groups): - Belizean",
    "State": "North Carolina",
    "percapita": 1.002618272
  },
  {
    "Ancestry": "West Indian (except Hispanic groups): - Belizean",
    "State": "New York",
    "percapita": 4.506683733
  },
  {
    "Ancestry": "West Indian (except Hispanic groups): - Belizean",
    "State": "Pennsylvania",
    "percapita": 0.598254083
  },
  {
    "Ancestry": "West Indian (except Hispanic groups): - Belizean",
    "State": "Georgia",
    "percapita": 1.137923115
  },
  {
    "Ancestry": "West Indian (except Hispanic groups): - Belizean",
    "State": "Missouri",
    "percapita": 0.249027432
  },
  {
    "Ancestry": "West Indian (except Hispanic groups): - Belizean",
    "State": "New Jersey",
    "percapita": 1.564077678
  },
  {
    "Ancestry": "West Indian (except Hispanic groups): - Belizean",
    "State": "Virginia",
    "percapita": 1.225035547
  },
  {
    "Ancestry": "West Indian (except Hispanic groups): - Belizean",
    "State": "California",
    "percapita": 5.531602345
  }
]